docci/__init__.py
docci/config.py
docci/file.py
docci/xlsx.py
docci/zip.py
docci-1.1.0.dist-info/WHEEL
docci-1.1.0.dist-info/METADATA
docci-1.1.0.dist-info/RECORD
