Metadata-Version: 2.1
Name: docci
Version: 1.1.0
Summary: Various document utils
Home-page: https://github.com/potykion/docci
License: MIT
Author: potykion
Author-email: potykion@gmail.com
Requires-Python: >=3.7,<4.0
Classifier: License :: OSI Approved :: MIT License
Classifier: Programming Language :: Python :: 3
Classifier: Programming Language :: Python :: 3.7
Classifier: Programming Language :: Python :: 3.8
Requires-Dist: openpyxl (>=3.0,<4.0)
Project-URL: Repository, https://github.com/potykion/docci
